{
  "@context": "https://www.w3.org/ns/activitystreams",
  "type": "SuggestNewCaseParticipant",
  "id": "https://for.example/0956f666-c1fe-4b8c-a11b-37b8cda1402c",
  "name": "https://vuls.example.com/finder-reporter SuggestNewCaseParticipant https://another.affected.vendor.example to https://vendor.example/psirt",
  "context": "https://vendor.example/case/18283771",
  "published": "2023-04-17T19:34:46+00:00",
  "updated": "2023-04-17T19:34:46+00:00",
  "summary": "Further testing indcates that Vendor-to-invite also has products affected by this vulnerability.",
  "actor": "https://vuls.example.com/finder-reporter",
  "target": "https://vendor.example/psirt",
  "object": "https://another.affected.vendor.example"
}